PyToPyd/download.py
PyToPyd/main.py
PyToPyd/pytopyd.ico
py_to_pyd-0.1.8.dist-info/LICENSE.txt
py_to_pyd-0.1.8.dist-info/METADATA
py_to_pyd-0.1.8.dist-info/WHEEL
py_to_pyd-0.1.8.dist-info/entry_points.txt
py_to_pyd-0.1.8.dist-info/top_level.txt
py_to_pyd-0.1.8.dist-info/RECORD
