Metadata-Version: 2.2
Name: py_to_pyd
Version: 0.1.8
Summary: Py To Pyd
Author: huang yi yi
Author-email: 363766687@qq.com
Requires-Python: >=3.6
License-File: LICENSE.txt
Requires-Dist: Cython>=3.0.10
Requires-Dist: pyfiglet>=1.0.1.post1
Requires-Dist: pyinstaller>=6.11.0
Requires-Dist: auto-py-to-exe>=2.45.0
Requires-Dist: requests
Requires-Dist: tqdm
Requires-Dist: colorama
Dynamic: author
Dynamic: author-email
Dynamic: description
Dynamic: description-content-type
Dynamic: requires-dist
Dynamic: requires-python
Dynamic: summary
